mldrift/__init__.py
mldrift/tabular/__init__.py
mldrift/tabular/_result_handler.py
mldrift/tabular/lightgbm_diff.py
mldrift/tabular/_utils/__init__.py
mldrift/tabular/_utils/constants.py
mldrift/tabular/_utils/pdutils.py
mldrift/tabular/utils/__init__.py
mldrift/tabular/utils/helper.py
mldrift-0.0.11.dist-info/LICENSE
mldrift-0.0.11.dist-info/METADATA
mldrift-0.0.11.dist-info/WHEEL
mldrift-0.0.11.dist-info/top_level.txt
mldrift-0.0.11.dist-info/RECORD
