Metadata-Version: 2.1
Name: mldrift
Version: 0.0.11
Summary: Data drift by ML, for ML.
Home-page: https://github.com/pypa/mldrift
Author: Cody Peterson
Author-email: cody.dkdc@gmail.com
License: UNKNOWN
Project-URL: Bug Tracker, https://github.com/lostmygithubaccount/mldrift/issues
Platform: UNKNOWN
Classifier: Programming Language :: Python :: 3
Classifier: License :: OSI Approved :: MIT License
Classifier: Operating System :: OS Independent
Requires-Python: >=3.6
License-File: LICENSE
Requires-Dist: mlflow
Requires-Dist: numpy
Requires-Dist: pandas
Requires-Dist: scikit-learn
Requires-Dist: lightgbm
